aigit/__init__.py
aigit/config_manager.py
aigit/git_interface.py
aigit/logger.py
aigit/main.py
aigit/openai_interface.py
aigit-0.1.9.dist-info/METADATA
aigit-0.1.9.dist-info/WHEEL
aigit-0.1.9.dist-info/entry_points.txt
aigit-0.1.9.dist-info/licenses/LICENSE
aigit-0.1.9.dist-info/RECORD
