Metadata-Version: 2.4
Name: aigit
Version: 0.1.9
Summary: A CLI tool to automatically generate git commit messages using OpenAI GPT-4
Project-URL: Homepage, https://github.com/nachoal/aig
Author-email: Ignacio Alonso <ignacio.alley@gmail.com>
License-File: LICENSE
Classifier: Development Status :: 3 - Alpha
Classifier: Intended Audience :: Developers
Classifier: License :: OSI Approved :: MIT License
Classifier: Programming Language :: Python :: 3
Classifier: Programming Language :: Python :: 3.6
Classifier: Programming Language :: Python :: 3.7
Classifier: Programming Language :: Python :: 3.8
Classifier: Programming Language :: Python :: 3.9
Classifier: Programming Language :: Python :: 3.10
Classifier: Topic :: Software Development :: Version Control :: Git
Requires-Python: >=3.6
Requires-Dist: gitpython
Requires-Dist: instructor
Requires-Dist: keyring
Requires-Dist: loguru
Requires-Dist: openai
Requires-Dist: python-dotenv
Requires-Dist: tiktoken
